gitlab_sync/__init__.py
gitlab_sync/cli.py
gitlab_sync/config.py
gitlab_sync/operations.py
gitlab_sync/repository.py
gitlab_sync/strategy.py
gitlab_sync-0.2.8.dist-info/METADATA
gitlab_sync-0.2.8.dist-info/WHEEL
gitlab_sync-0.2.8.dist-info/entry_points.txt
gitlab_sync-0.2.8.dist-info/top_level.txt
gitlab_sync-0.2.8.dist-info/RECORD
