Metadata-Version: 2.1
Name: gitlab-sync
Version: 0.2.8
Summary: synchronise GitLab repositories
Home-page: UNKNOWN
Author: Oliver Bristow
Author-email: github+pypi@oliverbristow.co.uk
License: UNKNOWN
Platform: UNKNOWN
Requires-Python: >=3.6
Requires-Dist: aiohttp
Requires-Dist: click
Requires-Dist: toml
Requires-Dist: voluptuous
Provides-Extra: test
Requires-Dist: pytest (>=3.9) ; extra == 'test'
Requires-Dist: pytest-docker ; extra == 'test'
Requires-Dist: grab ; extra == 'test'
Requires-Dist: requests ; extra == 'test'
